memoir/__init__.py
memoir/check_line.py
memoir/data/allmols_combined_transitions.csv
memoir_lpd-1.1.data/scripts/memoir
memoir_lpd-1.1.dist-info/METADATA
memoir_lpd-1.1.dist-info/WHEEL
memoir_lpd-1.1.dist-info/top_level.txt
memoir_lpd-1.1.dist-info/RECORD
