Metadata-Version: 2.1
Name: memoir-lpd
Version: 1.1
Summary: Spectral molecular line detection for ALMA Archive High Level Data Products.
Home-page: https://akdiaz.xyz/memoir
Author: Ana Karla Díaz Rodríguez
Author-email: diaz.rodriguez.a.k@gmail.com
Project-URL: Bug Tracker, https://github.com/akdiaz/LPD/issues
Classifier: Programming Language :: Python :: 3
Classifier: License :: OSI Approved :: MIT License
Classifier: Operating System :: OS Independent
Classifier: Intended Audience :: Science/Research
Classifier: Topic :: Scientific/Engineering :: Astronomy
Classifier: Topic :: Scientific/Engineering :: Physics
Requires-Python: >=3.0
Requires-Dist: astropy
Requires-Dist: importlib-resources
Requires-Dist: matplotlib
Requires-Dist: numpy
Requires-Dist: pandas
Requires-Dist: scipy
